linear_segment/__init__.py
linear_segment/bcpseg/__init__.py
linear_segment/bcpseg/bcp_segment.cpython-310-darwin.so
linear_segment/bcpseg/bcp_segment.cpython-311-darwin.so
linear_segment/bcpseg/bcp_segment.cpython-312-darwin.so
linear_segment/bcpseg/bcp_segment.cpython-313-darwin.so
linear_segment/bcpseg/bcp_segment.pxd
linear_segment/bcpseg/bcp_segment.pyx
linear_segment/bcpseg/offline_bcp.c
linear_segment/bcpseg/offline_bcp.h
linear_segment/bcpseg/online_bcp.c
linear_segment/bcpseg/online_bcp.h
linear_segment/bcpseg/utilities.c
linear_segment/cbseg/__init__.py
linear_segment/cbseg/cbs.h
linear_segment/cbseg/cbs_labeled.c
linear_segment/cbseg/cbs_structs.c
linear_segment/cbseg/cbseg.cpython-311-darwin.so
linear_segment/cbseg/cbseg.cpython-312-darwin.so
linear_segment/cbseg/cbseg.cpython-313-darwin.so
linear_segment/cbseg/cbseg.pxd
linear_segment/cbseg/cbseg.pyx
linear_segment/cbseg/utilities.c
linear_segment/segment.py
linear_segment-1.2.1.dist-info/LICENSE.md
linear_segment-1.2.1.dist-info/METADATA
linear_segment-1.2.1.dist-info/WHEEL
linear_segment-1.2.1.dist-info/RECORD
